mlgb/__init__.py
mlgb/data.py
mlgb/error.py
mlgb/fe.py
mlgb/main.py
mlgb/utils.py
mlgb/examples/faiss_search.py
mlgb/examples/tf_matching.py
mlgb/examples/tf_mtl.py
mlgb/examples/tf_ranking.py
mlgb/examples/torch_matching.py
mlgb/examples/torch_mtl.py
mlgb/examples/torch_ranking.py
mlgb/tf/agg.py
mlgb/tf/configs.py
mlgb/tf/functions.py
mlgb/tf/inputs.py
mlgb/tf/components/base.py
mlgb/tf/components/fbis.py
mlgb/tf/components/linears.py
mlgb/tf/components/retrieval.py
mlgb/tf/components/trms.py
mlgb/tf/models/matching.py
mlgb/tf/models/mtl.py
mlgb/tf/models/ranking.py
mlgb/tf/modules/matching.py
mlgb/tf/modules/ranking/multitask.py
mlgb/tf/modules/ranking/normal.py
mlgb/tf/modules/ranking/sequential.py
mlgb/torch/agg.py
mlgb/torch/configs.py
mlgb/torch/functions.py
mlgb/torch/inputs.py
mlgb/torch/components/base.py
mlgb/torch/components/fbis.py
mlgb/torch/components/linears.py
mlgb/torch/components/retrieval.py
mlgb/torch/components/trms.py
mlgb/torch/models/matching.py
mlgb/torch/models/mtl.py
mlgb/torch/models/ranking.py
mlgb/torch/modules/matching.py
mlgb/torch/modules/ranking/multitask.py
mlgb/torch/modules/ranking/normal.py
mlgb/torch/modules/ranking/sequential.py
mlgb-0.0.7.dist-info/LICENSE
mlgb-0.0.7.dist-info/METADATA
mlgb-0.0.7.dist-info/WHEEL
mlgb-0.0.7.dist-info/top_level.txt
mlgb-0.0.7.dist-info/RECORD
