Metadata-Version: 2.2
Name: mlgb
Version: 0.0.7
Summary: MLGB is a library that includes many models of CTR Prediction & Recommender System by TensorFlow & PyTorch.
Home-page: https://github.com/uliontse/mlgb
Author: UlionTse
Author-email: uliontse@outlook.com
License: Apache-2.0
Project-URL: Source, https://github.com/UlionTse/mlgb
Project-URL: Changelog, https://github.com/UlionTse/mlgb/blob/main/change_log.txt
Project-URL: Documentation, https://github.com/UlionTse/mlgb/blob/main/README.md
Keywords: Machine Learning,Deep Learning,CTR Prediction,Recommender System
Classifier: Development Status :: 5 - Production/Stable
Classifier: Intended Audience :: Developers
Classifier: License :: OSI Approved :: Apache Software License
Classifier: Programming Language :: Python :: 3 :: Only
Classifier: Programming Language :: Python :: 3.9
Classifier: Programming Language :: Python :: 3.10
Classifier: Programming Language :: Python :: 3.11
Classifier: Programming Language :: Python :: 3.12
Classifier: Topic :: Scientific/Engineering
Classifier: Topic :: Scientific/Engineering :: Artificial Intelligence
Classifier: Topic :: Software Development
Classifier: Topic :: Software Development :: Libraries
Classifier: Topic :: Software Development :: Libraries :: Python Modules
Requires-Python: >=3.9
License-File: LICENSE
Requires-Dist: numpy>=1.26.4
Requires-Dist: pandas>=1.5.3
Requires-Dist: scikit-learn>=1.6.1
Requires-Dist: torch>=2.1.0
Requires-Dist: tensorflow>=2.10.0
Provides-Extra: pypi
Requires-Dist: build>=1.2.2; extra == "pypi"
Requires-Dist: twine>=6.1.0; extra == "pypi"
Dynamic: author
Dynamic: author-email
Dynamic: classifier
Dynamic: description
Dynamic: description-content-type
Dynamic: home-page
Dynamic: keywords
Dynamic: license
Dynamic: project-url
Dynamic: provides-extra
Dynamic: requires-dist
Dynamic: requires-python
Dynamic: summary
